oqd_compiler_infrastructure/__init__.py
oqd_compiler_infrastructure/base.py
oqd_compiler_infrastructure/interface.py
oqd_compiler_infrastructure/rewriter.py
oqd_compiler_infrastructure/rule.py
oqd_compiler_infrastructure/walk.py
oqd_compiler_infrastructure-0.1.0.dist-info/LICENSE
oqd_compiler_infrastructure-0.1.0.dist-info/METADATA
oqd_compiler_infrastructure-0.1.0.dist-info/NOTICE
oqd_compiler_infrastructure-0.1.0.dist-info/WHEEL
oqd_compiler_infrastructure-0.1.0.dist-info/top_level.txt
oqd_compiler_infrastructure-0.1.0.dist-info/RECORD
