Metadata-Version: 2.1
Name: oqd-compiler-infrastructure
Version: 0.1.0
License: Apache 2.0
Project-URL: Homepage, https://github.com/OpenQuantumDesign/oqd-compiler-infrastructure
Project-URL: Repository, https://github.com/OpenQuantumDesign/oqd-compiler-infrastructure.git
Project-URL: Issues, https://github.com/OpenQuantumDesign/oqd-compiler-infrastructure/issues
Keywords: quantum,computing,compiler,transpilation
Classifier: Development Status :: 3 - Alpha
Classifier: Intended Audience :: Science/Research 
Classifier: Topic :: Scientific/Engineering :: Physics
Classifier: Topic :: Scientific/Engineering :: Information Analysis
Classifier: Topic :: Software Development :: Compilers
Classifier: License :: OSI Approved :: Apache Software License
Classifier: Programming Language :: Python :: 3
Classifier: Programming Language :: Python :: 3.10
Classifier: Programming Language :: Python :: 3.11
Classifier: Programming Language :: Python :: 3.12
Requires-Python: >=3.10
License-File: LICENSE
License-File: NOTICE
Requires-Dist: pydantic
Provides-Extra: docs
Requires-Dist: pymdown-extensions; extra == "docs"
Requires-Dist: mkdocstrings; extra == "docs"
Requires-Dist: mkdocs-material; extra == "docs"
Requires-Dist: mkdocstrings-python; extra == "docs"
Requires-Dist: mdx-truly-sane-lists; extra == "docs"
Provides-Extra: test
Requires-Dist: unittest-prettify; extra == "test"
